{"cameraMode":{"drawMode":0,"name":"Shaded","section":"Shading Mode"},"sceneLighting":true,"audioPlay":false,"sceneViewState":{"m_AlwaysRefresh":false,"showFog":true,"showSkybox":true,"showFlares":true,"showImageEffects":true,"showParticleSystems":true,"showVisualEffectGraphs":true,"m_FxEnabled":true},"in2DMode":false,"pivot":{"x":-3.196303129196167,"y":-4.391848564147949,"z":6.411417007446289},"rotation":{"x":0.2581486403942108,"y":-0.2425471693277359,"z":0.06712569296360016,"w":0.9327606558799744},"size":0.5931382179260254,"orthographic":false}