{"cameraMode":{"drawMode":0,"name":"Shaded","section":"Shading Mode"},"sceneLighting":true,"audioPlay":false,"sceneViewState":{"m_AlwaysRefresh":false,"showFog":true,"showSkybox":true,"showFlares":true,"showImageEffects":true,"showParticleSystems":true,"showVisualEffectGraphs":true,"m_FxEnabled":true},"in2DMode":false,"pivot":{"x":-2.411022901535034,"y":-3.0657715797424318,"z":3.0384716987609865},"rotation":{"x":0.0,"y":0.999989926815033,"z":0.0,"w":-0.004499985370784998},"size":3.4327261447906496,"orthographic":false}